{"name":"GET comments without parameter","id":"testing-get-comments-jsonplaceholder;get-comments-without-parameter","testSteps":[{"number":1,"description":"Given Get comments without any parameter","duration":11,"startTime":"2023-01-20T18:55:35.826+07:00[Asia/Bangkok]","result":"SUCCESS","precondition":false,"level":0,"children":[{"number":2,"description":"Get list comments without parameter","duration":2,"startTime":"2023-01-20T18:55:35.833+07:00[Asia/Bangkok]","result":"SUCCESS","precondition":false,"level":1}]},{"number":3,"description":"When Send request get list comments without param","duration":941,"startTime":"2023-01-20T18:55:35.838+07:00[Asia/Bangkok]","result":"SUCCESS","precondition":false,"level":0,"children":[{"number":4,"description":"GET https://jsonplaceholder.typicode.com\r","duration":0,"startTime":"2023-01-20T18:55:36.778+07:00[Asia/Bangkok]","result":"SUCCESS","restQuery":{"method":"GET","path":"https://jsonplaceholder.typicode.com\r","content":"\r","contentType":"null","requestHeaders":"Accept\u003d*/*\r","requestCookies":"\r","responseHeaders":"Date: Fri, 20 Jan 2023 11:55:36 GMT\r\nContent-Type: text/html; charset\u003dUTF-8\r\nTransfer-Encoding: chunked\r\nConnection: keep-alive\r\nX-Powered-By: Express\r\nX-Ratelimit-Limit: 1000\r\nX-Ratelimit-Remaining: 999\r\nX-Ratelimit-Reset: 1674143830\r\nVary: Origin, Accept-Encoding\r\nAccess-Control-Allow-Credentials: true\r\nCache-Control: public, max-age\u003d43200\r\nLast-Modified: Thu, 19 Jan 2023 13:00:03 GMT\r\nVia: 1.1 vegur\r\nCF-Cache-Status: HIT\r\nAge: 14037\r\nServer-Timing: cf-q-config;dur\u003d6.9999987317715e-06\r\nReport-To: {\"endpoints\":[{\"url\":\"https:\\/\\/a.nel.cloudflare.com\\/report\\/v3?s\u003dmsmchuUqHixzd0iYmCa1y97q%2BcAVWoQWIksRU34JnxXXs4ZvJiAFBLXZlkR1EL5OZ3VKPGLEZgjJvVzl%2BATjMzbAdpeBPiaJRvu7jsvFT3cCXBFUqrkULef5BtpuCUR7UjJkKncHn%2BwzgDsAmLqK\"}],\"group\":\"cf-nel\",\"max_age\":604800}\r\nNEL: {\"success_fraction\":0,\"report_to\":\"cf-nel\",\"max_age\":604800}\r\nServer: cloudflare\r\nCF-RAY: 78c79f417d2b2b73-LAX\r\nContent-Encoding: gzip\r\nalt-svc: h3\u003d\":443\"; ma\u003d86400, h3-29\u003d\":443\"; ma\u003d86400\r","responseCookies":"\r","responseBody":"\u003chtml lang\u003d\"en\"\u003e\n  \u003chead\u003e\n    \u003cmeta charset\u003d\"utf-8\"/\u003e\n    \u003cmeta name\u003d\"viewport\" content\u003d\"width\u003ddevice-width, initial-scale\u003d1, shrink-to-fit\u003dno\"/\u003e\n    \u003clink rel\u003d\"stylesheet\" href\u003d\"/style.css\"/\u003e\n    \u003clink rel\u003d\"stylesheet\" href\u003d\"https://cdnjs.cloudflare.com/ajax/libs/prism/1.21.0/themes/prism-tomorrow.min.css\"/\u003e\n    \u003ctitle\u003eJSONPlaceholder - Free Fake REST API\u003c/title\u003e\n    \u003cscript async\u003d\"async\" src\u003d\"https://www.googletagmanager.com/gtag/js?id\u003dG-E3C3GCQVBN\"/\u003e\n    \u003cscript\u003e\n    window.dataLayer \u003d window.dataLayer || []\n    function gtag() {\n      dataLayer.push(arguments)\n    }\n    gtag(\u0027js\u0027, new Date())\n\n    gtag(\u0027config\u0027, \u0027G-E3C3GCQVBN\u0027)\n  \u003c/script\u003e\n  \u003c/head\u003e\n  \u003cbody class\u003d\"px-2\"\u003e\n    \u003cheader class\u003d\"         container         mx-auto         max-w-4xl         flex flex-col         md:flex-row         justify-between         py-one         mb-three       \"\u003e\n      \u003ch1\u003e\n        \u003ca shape\u003d\"rect\" class\u003d\"font-bold no-underline\" href\u003d\"/\"\u003eJSONPlaceholder\u003c/a\u003e\n      \u003c/h1\u003e\n      \u003cnav\u003e\n        \u003cul class\u003d\"flex\"\u003e\n          \u003cli\u003e\n            \u003ca shape\u003d\"rect\" class\u003d\"mr-4 no-underline\" href\u003d\"/guide\"\u003eGuide\u003c/a\u003e\n          \u003c/li\u003e\n          \u003cli\u003e\n            \u003ca shape\u003d\"rect\" class\u003d\"mr-4 no-underline\" href\u003d\"https://github.com/sponsors/typicode\"\u003eSponsor this project\u003c/a\u003e\n          \u003c/li\u003e\n          \u003cli\u003e\n            \u003ca shape\u003d\"rect\" class\u003d\"mr-4 no-underline\" href\u003d\"https://blog.typicode.com\"\u003eBlog\u003c/a\u003e\n          \u003c/li\u003e\n          \u003cli\u003e\n            \u003ca shape\u003d\"rect\" class\u003d\"no-underline\" href\u003d\"https://my-json-server.typicode.com\"\u003eMy JSON Server\u003c/a\u003e\n          \u003c/li\u003e\n        \u003c/ul\u003e\n      \u003c/nav\u003e\n    \u003c/header\u003e\n    \u003cdiv\u003e\n      \u003csection id\u003d\"hero\" class\u003d\"-mt-three py-36 mb-six -mx-2\"\u003e\n        \u003cdiv class\u003d\"container mx-auto max-w-4xl\"\u003e\n          \u003cspan class\u003d\"text-6xl bold\"\u003e{JSON} Placeholder\u003c/span\u003e\n          \u003ch1 class\u003d\"mt-two text-lg\"\u003e\nFree fake API for testing and prototyping.\n\u003c/h1\u003e\n          \u003cp class\u003d\"mb-one text-lg\"\u003e\n\nPowered by\n            \u003ca shape\u003d\"rect\" href\u003d\"https://github.com/typicode/json-server\"\u003eJSON Server\u003c/a\u003e\n\n+\n            \u003ca shape\u003d\"rect\" href\u003d\"https://github.com/typicode/lowdb\"\u003eLowDB\u003c/a\u003e\n. Tested with             \u003ca shape\u003d\"rect\" href\u003d\"https://github.com/typicode/xv\"\u003eXV\u003c/a\u003e\n.\n          \u003c/p\u003e\n          \u003cp\u003e\nAs of Oct 2022,             \u003cb\u003eserving ~1.7 billion requests each month\u003c/b\u003e\n.          \u003c/p\u003e\n        \u003c/div\u003e\n      \u003c/section\u003e\n      \u003csection class\u003d\"container mx-auto max-w-4xl mb-six\"\u003e\n        \u003ch2 class\u003d\"text-2xl mb-one\"\u003eSponsors\u003c/h2\u003e\n        \u003cp class\u003d\"mb-two\"\u003e\n\nJSONPlaceholder is supported by the following companies and\n          \u003ca shape\u003d\"rect\" href\u003d\"https://github.com/sponsors/typicode\"\u003eSponsors\u003c/a\u003e\n on GitHub, check\nthem out 💖\n        \u003c/p\u003e\n        \u003cp\u003e\n          \u003ca shape\u003d\"rect\" href\u003d\"https://tryretool.com/?utm_source\u003dsponsor\u0026amp;utm_campaign\u003dtypicode\" target\u003d\"_blank\"\u003e\n            \u003cimg class\u003d\"h-three mb-two\" src\u003d\"https://i.imgur.com/IBItATn.png\"/\u003e\n          \u003c/a\u003e\n        \u003c/p\u003e\n        \u003cp\u003e\n          \u003ca shape\u003d\"rect\" href\u003d\"https://mockend.com\" target\u003d\"_blank\"\u003e\n            \u003cimg class\u003d\"h-three mb-two\" src\u003d\"mockend.svg\"/\u003e\n          \u003c/a\u003e\n        \u003c/p\u003e\n        \u003cp\u003e\n          \u003ca shape\u003d\"rect\" href\u003d\"https://megafamous.com/buy-instagram-followers\" target\u003d\"_blank\"\u003e\n            \u003cimg class\u003d\"h-three mb-two\" src\u003d\"megafamous.png\"/\u003e\n          \u003c/a\u003e\n        \u003c/p\u003e\n        \u003cp class\u003d\"my-two\"\u003e\n          \u003ca shape\u003d\"rect\" href\u003d\"https://github.com/sponsors/typicode\"\u003eYour company logo here\u003c/a\u003e\n        \u003c/p\u003e\n      \u003c/section\u003e\n      \u003csection class\u003d\"container mx-auto max-w-4xl mb-four\"\u003e\n        \u003ch2 class\u003d\"text-2xl mb-one\"\u003eTry it\u003c/h2\u003e\n        \u003cp\u003eRun this code here, in a console or from any site:\u003c/p\u003e\n        \u003cpre\u003e\n          \u003ccode class\u003d\"language-javascript\" id\u003d\"example\"\u003efetch(\u0027https://jsonplaceholder.typicode.com/todos/1\u0027)\n      .then(response \u003d\u0026gt; response.json())\n      .then(json \u003d\u0026gt; console.log(json))\u003c/code\u003e\n        \u003c/pre\u003e\n        \u003cbutton type\u003d\"submit\" class\u003d\"bg-green-500 hover:bg-green-700 text-white font-bold py-quarter my-quarter px-4 rounded\" id\u003d\"run-button\"\u003e\nRun script\n\u003c/button\u003e\n        \u003cpre\u003e\n          \u003ccode class\u003d\"language-javascript\" id\u003d\"result\"\u003e{}\u003c/code\u003e\n        \u003c/pre\u003e\n        \u003cp class\u003d\"invisible\" id\u003d\"run-message\"\u003e\nCongrats you\u0027ve made your first call to JSONPlaceholder! 😃 🎉\n\u003c/p\u003e\n        \u003cdiv class\u003d\"horizontal flat\" data-ea-publisher\u003d\"jsonplaceholdertypicodecom\" data-ea-style\u003d\"stickybox\" data-ea-keywords\u003d\"javascript|typescript|python|ruby|swift|react|vue|web|testing|frontend|front-end|backend|back-end\" data-ea-manual\u003d\"true\"/\u003e\n      \u003c/section\u003e\n      \u003cmain class\u003d\"container mx-auto max-w-4xl\"\u003e\n        \u003ch2\u003eWhen to use\u003c/h2\u003e\n        \u003cp\u003e\nJSONPlaceholder is a free online REST API that you can use           \u003cstrong\u003ewhenever you need some fake data\u003c/strong\u003e\n. It can be in a README on GitHub, for a demo on CodeSandbox, in code examples on Stack Overflow, ...or simply to test things locally.        \u003c/p\u003e\n        \u003ch2\u003eResources\u003c/h2\u003e\n        \u003cp\u003eJSONPlaceholder comes with a set of 6 common resources:\u003c/p\u003e\n        \u003ctable\u003e\n          \u003cthead\u003e\n            \u003ctr\u003e\n              \u003cth colspan\u003d\"1\" rowspan\u003d\"1\"/\u003e\n              \u003cth colspan\u003d\"1\" rowspan\u003d\"1\"/\u003e\n            \u003c/tr\u003e\n          \u003c/thead\u003e\n          \u003ctbody\u003e\n            \u003ctr\u003e\n              \u003ctd colspan\u003d\"1\" rowspan\u003d\"1\"\u003e\n                \u003ca shape\u003d\"rect\" href\u003d\"/posts\"\u003e/posts\u003c/a\u003e\n              \u003c/td\u003e\n              \u003ctd colspan\u003d\"1\" rowspan\u003d\"1\"\u003e100 posts\u003c/td\u003e\n            \u003c/tr\u003e\n            \u003ctr\u003e\n              \u003ctd colspan\u003d\"1\" rowspan\u003d\"1\"\u003e\n                \u003ca shape\u003d\"rect\" href\u003d\"/comments\"\u003e/comments\u003c/a\u003e\n              \u003c/td\u003e\n              \u003ctd colspan\u003d\"1\" rowspan\u003d\"1\"\u003e500 comments\u003c/td\u003e\n            \u003c/tr\u003e\n            \u003ctr\u003e\n              \u003ctd colspan\u003d\"1\" rowspan\u003d\"1\"\u003e\n                \u003ca shape\u003d\"rect\" href\u003d\"/albums\"\u003e/albums\u003c/a\u003e\n              \u003c/td\u003e\n              \u003ctd colspan\u003d\"1\" rowspan\u003d\"1\"\u003e100 albums\u003c/td\u003e\n            \u003c/tr\u003e\n            \u003ctr\u003e\n              \u003ctd colspan\u003d\"1\" rowspan\u003d\"1\"\u003e\n                \u003ca shape\u003d\"rect\" href\u003d\"/photos\"\u003e/photos\u003c/a\u003e\n              \u003c/td\u003e\n              \u003ctd colspan\u003d\"1\" rowspan\u003d\"1\"\u003e5000 photos\u003c/td\u003e\n            \u003c/tr\u003e\n            \u003ctr\u003e\n              \u003ctd colspan\u003d\"1\" rowspan\u003d\"1\"\u003e\n                \u003ca shape\u003d\"rect\" href\u003d\"/todos\"\u003e/todos\u003c/a\u003e\n              \u003c/td\u003e\n              \u003ctd colspan\u003d\"1\" rowspan\u003d\"1\"\u003e200 todos\u003c/td\u003e\n            \u003c/tr\u003e\n            \u003ctr\u003e\n              \u003ctd colspan\u003d\"1\" rowspan\u003d\"1\"\u003e\n                \u003ca shape\u003d\"rect\" href\u003d\"/users\"\u003e/users\u003c/a\u003e\n              \u003c/td\u003e\n              \u003ctd colspan\u003d\"1\" rowspan\u003d\"1\"\u003e10 users\u003c/td\u003e\n            \u003c/tr\u003e\n          \u003c/tbody\u003e\n        \u003c/table\u003e\n        \u003cp\u003e\n          \u003cstrong\u003eNote\u003c/strong\u003e\n: resources have relations. For example: posts have many comments, albums have many photos, ... see           \u003ca shape\u003d\"rect\" href\u003d\"/guide\"\u003eguide\u003c/a\u003e\n for the full list.        \u003c/p\u003e\n        \u003ch2\u003eRoutes\u003c/h2\u003e\n        \u003cp\u003eAll HTTP methods are supported. You can use http or https for your requests.\u003c/p\u003e\n        \u003ctable\u003e\n          \u003cthead\u003e\n            \u003ctr\u003e\n              \u003cth colspan\u003d\"1\" rowspan\u003d\"1\"/\u003e\n              \u003cth colspan\u003d\"1\" rowspan\u003d\"1\"/\u003e\n            \u003c/tr\u003e\n          \u003c/thead\u003e\n          \u003ctbody\u003e\n            \u003ctr\u003e\n              \u003ctd colspan\u003d\"1\" rowspan\u003d\"1\"\u003eGET\u003c/td\u003e\n              \u003ctd colspan\u003d\"1\" rowspan\u003d\"1\"\u003e\n                \u003ca shape\u003d\"rect\" href\u003d\"/posts\"\u003e/posts\u003c/a\u003e\n              \u003c/td\u003e\n            \u003c/tr\u003e\n            \u003ctr\u003e\n              \u003ctd colspan\u003d\"1\" rowspan\u003d\"1\"\u003eGET\u003c/td\u003e\n              \u003ctd colspan\u003d\"1\" rowspan\u003d\"1\"\u003e\n                \u003ca shape\u003d\"rect\" href\u003d\"/posts/1\"\u003e/posts/1\u003c/a\u003e\n              \u003c/td\u003e\n            \u003c/tr\u003e\n            \u003ctr\u003e\n              \u003ctd colspan\u003d\"1\" rowspan\u003d\"1\"\u003eGET\u003c/td\u003e\n              \u003ctd colspan\u003d\"1\" rowspan\u003d\"1\"\u003e\n                \u003ca shape\u003d\"rect\" href\u003d\"/posts/1/comments\"\u003e/posts/1/comments\u003c/a\u003e\n              \u003c/td\u003e\n            \u003c/tr\u003e\n            \u003ctr\u003e\n              \u003ctd colspan\u003d\"1\" rowspan\u003d\"1\"\u003eGET\u003c/td\u003e\n              \u003ctd colspan\u003d\"1\" rowspan\u003d\"1\"\u003e\n                \u003ca shape\u003d\"rect\" href\u003d\"/comments?postId\u003d1\"\u003e/comments?postId\u003d1\u003c/a\u003e\n              \u003c/td\u003e\n            \u003c/tr\u003e\n            \u003ctr\u003e\n              \u003ctd colspan\u003d\"1\" rowspan\u003d\"1\"\u003ePOST\u003c/td\u003e\n              \u003ctd colspan\u003d\"1\" rowspan\u003d\"1\"\u003e/posts\u003c/td\u003e\n            \u003c/tr\u003e\n            \u003ctr\u003e\n              \u003ctd colspan\u003d\"1\" rowspan\u003d\"1\"\u003ePUT\u003c/td\u003e\n              \u003ctd colspan\u003d\"1\" rowspan\u003d\"1\"\u003e/posts/1\u003c/td\u003e\n            \u003c/tr\u003e\n            \u003ctr\u003e\n              \u003ctd colspan\u003d\"1\" rowspan\u003d\"1\"\u003ePATCH\u003c/td\u003e\n              \u003ctd colspan\u003d\"1\" rowspan\u003d\"1\"\u003e/posts/1\u003c/td\u003e\n            \u003c/tr\u003e\n            \u003ctr\u003e\n              \u003ctd colspan\u003d\"1\" rowspan\u003d\"1\"\u003eDELETE\u003c/td\u003e\n              \u003ctd colspan\u003d\"1\" rowspan\u003d\"1\"\u003e/posts/1\u003c/td\u003e\n            \u003c/tr\u003e\n          \u003c/tbody\u003e\n        \u003c/table\u003e\n        \u003cp\u003e\n          \u003cstrong\u003eNote\u003c/strong\u003e\n: see           \u003ca shape\u003d\"rect\" href\u003d\"/guide\"\u003eguide\u003c/a\u003e\n for usage examples.        \u003c/p\u003e\n        \u003ch2\u003eUse your own data\u003c/h2\u003e\n        \u003cp\u003e\nWith our sponsor           \u003ca shape\u003d\"rect\" href\u003d\"https://mockend.com\"\u003eMockend\u003c/a\u003e\n and a simple GitHub repo, you can have your own fake online REST server in seconds.        \u003c/p\u003e\n      \u003c/main\u003e\n      \u003cscript\u003e\n  // Use http or https based on location.protocol\n  var example \u003d document.getElementById(\u0027example\u0027);\n  example.textContent \u003d example.textContent.replace(\u0027http:\u0027, location.protocol);\n\n  // Highlight result element\n  var result \u003d document.getElementById(\u0027result\u0027);\n\n  // Run example\n  var runButton \u003d document.getElementById(\u0027run-button\u0027);\n  runButton.onclick \u003d function () {\n    var root \u003d location.protocol + \u0027//jsonplaceholder.typicode.com\u0027;\n    var runMessage \u003d document.getElementById(\u0027run-message\u0027);\n\n    fetch(\u0027https://jsonplaceholder.typicode.com/todos/1\u0027)\n      .then((response) \u003d\u0026gt; response.json())\n      .then((json) \u003d\u0026gt; {\n        var str \u003d JSON.stringify(json, null, \u0027  \u0027);\n\n        // Format result\n        result.innerHTML \u003d Prism.highlight(\n          str,\n          Prism.languages.javascript,\n          \u0027javascript\u0027,\n        );\n\n        runMessage.className \u003d \u0027\u0027;\n      });\n  };\n\u003c/script\u003e\n    \u003c/div\u003e\n    \u003cfooter class\u003d\"container mx-auto max-w-4xl mt-four\"\u003e\n      \u003cdiv class\u003d\"mb-one\"\u003e\n        \u003ca shape\u003d\"rect\" href\u003d\"https://github.com/users/typicode/sponsorship\"\u003e\n          \u003cstrong\u003eYou can sponsor this project (and others) on GitHub\u003c/strong\u003e\n        \u003c/a\u003e\n      \u003c/div\u003e\n      \u003cdiv class\u003d\"mb-one\"\u003e\n\nCoded and maintained with ❤️ by\n        \u003ca shape\u003d\"rect\" href\u003d\"https://github.com/typicode\"\u003etypicode\u003c/a\u003e\n © 2022\n      \u003c/div\u003e\n    \u003c/footer\u003e\n    \u003cscript src\u003d\"https://cdnjs.cloudflare.com/ajax/libs/prism/1.21.0/prism.min.js\"/\u003e\n    \u003cscript src\u003d\"https://media.ethicalads.io/media/client/ethicalads.min.js\"/\u003e\n    \u003cscript src\u003d\"/script.js\"/\u003e\n    \u003cscript defer\u003d\"defer\" src\u003d\"https://static.cloudflareinsights.com/beacon.min.js/vaafb692b2aea4879b33c060e79fe94621666317369993\" integrity\u003d\"sha512-0ahDYl866UMhKuYcW078ScMalXqtFJggm7TmlUtp0UlD4eQk0Ixfnm5ykXKvGJNFjLMoortdseTfsRT8oCfgGA\u003d\u003d\" data-cf-beacon\u003d\"{\u0026quot;rayId\u0026quot;:\u0026quot;78c79f417d2b2b73\u0026quot;,\u0026quot;version\u0026quot;:\u0026quot;2022.11.3\u0026quot;,\u0026quot;r\u0026quot;:1,\u0026quot;token\u0026quot;:\u0026quot;2f059cbf58a24e59854ee0884c97b166\u0026quot;,\u0026quot;si\u0026quot;:100}\" crossorigin\u003d\"anonymous\"/\u003e\n  \u003c/body\u003e\n\u003c/html\u003e","statusCode":200},"precondition":false,"level":1}]},{"number":5,"description":"Then Should return comments with status code 200","duration":3,"startTime":"2023-01-20T18:55:36.780+07:00[Asia/Bangkok]","result":"SUCCESS","precondition":false,"level":0},{"number":6,"description":"And Response body page should be page","duration":2,"startTime":"2023-01-20T18:55:36.783+07:00[Asia/Bangkok]","result":"SUCCESS","precondition":false,"level":0},{"number":7,"description":"And Validate json schema list comments","duration":11,"startTime":"2023-01-20T18:55:36.785+07:00[Asia/Bangkok]","exception":{"errorType":"net.serenitybdd.core.exceptions.UnrecognisedException","stackTrace":[{"declaringClass":"com.fasterxml.jackson.core.JsonParser","methodName":"_constructError","fileName":"JsonParser.java","lineNumber":2337},{"declaringClass":"com.fasterxml.jackson.core.base.ParserMinimalBase","methodName":"_reportError","fileName":"ParserMinimalBase.java","lineNumber":710},{"declaringClass":"com.fasterxml.jackson.core.base.ParserMinimalBase","methodName":"_reportUnexpectedChar","fileName":"ParserMinimalBase.java","lineNumber":635},{"declaringClass":"com.fasterxml.jackson.core.json.ReaderBasedJsonParser","methodName":"_handleOddValue","fileName":"ReaderBasedJsonParser.java","lineNumber":1952},{"declaringClass":"com.fasterxml.jackson.core.json.ReaderBasedJsonParser","methodName":"nextToken","fileName":"ReaderBasedJsonParser.java","lineNumber":781},{"declaringClass":"com.fasterxml.jackson.databind.MappingIterator","methodName":"hasNextValue","fileName":"MappingIterator.java","lineNumber":243},{"declaringClass":"com.github.fge.jackson.JsonNodeReader","methodName":"readNode","fileName":"JsonNodeReader.java","lineNumber":149},{"declaringClass":"com.github.fge.jackson.JsonNodeReader","methodName":"fromReader","fileName":"JsonNodeReader.java","lineNumber":129},{"declaringClass":"com.github.fge.jackson.JsonLoader","methodName":"fromReader","fileName":"JsonLoader.java","lineNumber":186},{"declaringClass":"com.github.fge.jackson.JsonLoader","methodName":"fromString","fileName":"JsonLoader.java","lineNumber":199},{"declaringClass":"io.restassured.module.jsv.JsonSchemaValidator","methodName":"matchesSafely","fileName":"JsonSchemaValidator.java","lineNumber":214},{"declaringClass":"io.restassured.module.jsv.JsonSchemaValidator","methodName":"matchesSafely","fileName":"JsonSchemaValidator.java","lineNumber":75},{"declaringClass":"io.restassured.assertion.BodyMatcher","methodName":"validate","fileName":"BodyMatcher.groovy","lineNumber":76},{"declaringClass":"groovy.lang.MetaMethod","methodName":"doMethodInvoke","fileName":"MetaMethod.java","lineNumber":323},{"declaringClass":"groovy.lang.MetaClassImpl","methodName":"invokeMethod","fileName":"MetaClassImpl.java","lineNumber":1034},{"declaringClass":"groovy.lang.Closure","methodName":"call","fileName":"Closure.java","lineNumber":412},{"declaringClass":"groovy.lang.Closure","methodName":"call","fileName":"Closure.java","lineNumber":428},{"declaringClass":"io.restassured.assertion.BodyMatcherGroup","methodName":"validate","fileName":"BodyMatcherGroup.groovy","lineNumber":47},{"declaringClass":"io.restassured.internal.ResponseSpecificationImpl","methodName":"validateResponseIfRequired","fileName":"ResponseSpecificationImpl.groovy","lineNumber":674},{"declaringClass":"io.restassured.internal.ResponseSpecificationImpl","methodName":"body","fileName":"ResponseSpecificationImpl.groovy","lineNumber":98},{"declaringClass":"io.restassured.internal.ValidatableResponseOptionsImpl","methodName":"body","fileName":"ValidatableResponseOptionsImpl.java","lineNumber":238},{"declaringClass":"io.restassured.internal.ValidatableResponseImpl","methodName":"super$2$body","fileName":"ValidatableResponseImpl.groovy","lineNumber":-1},{"declaringClass":"groovy.lang.MetaMethod","methodName":"doMethodInvoke","fileName":"MetaMethod.java","lineNumber":323},{"declaringClass":"groovy.lang.MetaClassImpl","methodName":"invokeMethod","fileName":"MetaClassImpl.java","lineNumber":1267},{"declaringClass":"io.restassured.internal.ValidatableResponseImpl","methodName":"body","fileName":"ValidatableResponseImpl.groovy","lineNumber":293},{"declaringClass":"io.restassured.internal.ValidatableResponseImpl","methodName":"body","fileName":"ValidatableResponseImpl.groovy","lineNumber":-1},{"declaringClass":"starter.JsonPlaceHolder.Comments.GetCommentsStepDef","methodName":"validateJsonSchemaListComments","fileName":"GetCommentsStepDef.java","lineNumber":46},{"declaringClass":"io.cucumber.java.Invoker","methodName":"doInvoke","fileName":"Invoker.java","lineNumber":66},{"declaringClass":"io.cucumber.java.Invoker","methodName":"invoke","fileName":"Invoker.java","lineNumber":24},{"declaringClass":"io.cucumber.java.AbstractGlueDefinition","methodName":"invokeMethod","fileName":"AbstractGlueDefinition.java","lineNumber":47},{"declaringClass":"io.cucumber.java.JavaStepDefinition","methodName":"execute","fileName":"JavaStepDefinition.java","lineNumber":29},{"declaringClass":"io.cucumber.core.runner.CoreStepDefinition","methodName":"execute","fileName":"CoreStepDefinition.java","lineNumber":66},{"declaringClass":"io.cucumber.core.runner.PickleStepDefinitionMatch","methodName":"runStep","fileName":"PickleStepDefinitionMatch.java","lineNumber":63},{"declaringClass":"io.cucumber.core.runner.TestStep","methodName":"executeStep","fileName":"TestStep.java","lineNumber":92},{"declaringClass":"io.cucumber.core.runner.TestStep","methodName":"run","fileName":"TestStep.java","lineNumber":64},{"declaringClass":"io.cucumber.core.runner.PickleStepTestStep","methodName":"run","fileName":"PickleStepTestStep.java","lineNumber":51},{"declaringClass":"io.cucumber.core.runner.TestCase","methodName":"run","fileName":"TestCase.java","lineNumber":104},{"declaringClass":"io.cucumber.core.runner.Runner","methodName":"runPickle","fileName":"Runner.java","lineNumber":73},{"declaringClass":"io.cucumber.junit.FeatureRunner","methodName":"runChild","fileName":"FeatureRunner.java","lineNumber":135},{"declaringClass":"io.cucumber.junit.FeatureRunner","methodName":"runChild","fileName":"FeatureRunner.java","lineNumber":27},{"declaringClass":"io.cucumber.junit.CucumberSerenityRunner","methodName":"runChild","fileName":"CucumberSerenityRunner.java","lineNumber":258},{"declaringClass":"io.cucumber.junit.CucumberSerenityRunner","methodName":"runChild","fileName":"CucumberSerenityRunner.java","lineNumber":57}]},"result":"ERROR","precondition":false,"level":0}],"userStory":{"id":"testing-get-comments-jsonplaceholder","storyName":"Testing GET comments JsonPlaceHolder","path":"classpath:features/JsonPlaceHolder/Comments/GetComments.feature","type":"feature"},"featureTag":{"name":"Comments/Testing GET comments JsonPlaceHolder","type":"feature","displayName":"Comments/Testing GET comments JsonPlaceHolder"},"title":"GET comments without parameter","description":"","tags":[{"name":"Comments/Testing GET comments JsonPlaceHolder","type":"feature","displayName":"Testing GET comments JsonPlaceHolder"},{"name":"Json place holder/Comments","type":"capability","displayName":"Comments"},{"name":"GroupProject","type":"tag","displayName":"GroupProject"},{"name":"Json place holder","type":"theme","displayName":"Json place holder"},{"name":"Positive-Case","type":"tag","displayName":"Positive-Case"}],"startTime":"2023-01-20T18:55:35.817+07:00[Asia/Bangkok]","duration":981,"testFailureCause":{"errorType":"net.serenitybdd.core.exceptions.UnrecognisedException","stackTrace":[{"declaringClass":"com.fasterxml.jackson.core.JsonParser","methodName":"_constructError","fileName":"JsonParser.java","lineNumber":2337},{"declaringClass":"com.fasterxml.jackson.core.base.ParserMinimalBase","methodName":"_reportError","fileName":"ParserMinimalBase.java","lineNumber":710},{"declaringClass":"com.fasterxml.jackson.core.base.ParserMinimalBase","methodName":"_reportUnexpectedChar","fileName":"ParserMinimalBase.java","lineNumber":635},{"declaringClass":"com.fasterxml.jackson.core.json.ReaderBasedJsonParser","methodName":"_handleOddValue","fileName":"ReaderBasedJsonParser.java","lineNumber":1952},{"declaringClass":"com.fasterxml.jackson.core.json.ReaderBasedJsonParser","methodName":"nextToken","fileName":"ReaderBasedJsonParser.java","lineNumber":781},{"declaringClass":"com.fasterxml.jackson.databind.MappingIterator","methodName":"hasNextValue","fileName":"MappingIterator.java","lineNumber":243},{"declaringClass":"com.github.fge.jackson.JsonNodeReader","methodName":"readNode","fileName":"JsonNodeReader.java","lineNumber":149},{"declaringClass":"com.github.fge.jackson.JsonNodeReader","methodName":"fromReader","fileName":"JsonNodeReader.java","lineNumber":129},{"declaringClass":"com.github.fge.jackson.JsonLoader","methodName":"fromReader","fileName":"JsonLoader.java","lineNumber":186},{"declaringClass":"com.github.fge.jackson.JsonLoader","methodName":"fromString","fileName":"JsonLoader.java","lineNumber":199},{"declaringClass":"io.restassured.module.jsv.JsonSchemaValidator","methodName":"matchesSafely","fileName":"JsonSchemaValidator.java","lineNumber":214},{"declaringClass":"io.restassured.module.jsv.JsonSchemaValidator","methodName":"matchesSafely","fileName":"JsonSchemaValidator.java","lineNumber":75},{"declaringClass":"io.restassured.assertion.BodyMatcher","methodName":"validate","fileName":"BodyMatcher.groovy","lineNumber":76},{"declaringClass":"groovy.lang.MetaMethod","methodName":"doMethodInvoke","fileName":"MetaMethod.java","lineNumber":323},{"declaringClass":"groovy.lang.MetaClassImpl","methodName":"invokeMethod","fileName":"MetaClassImpl.java","lineNumber":1034},{"declaringClass":"groovy.lang.Closure","methodName":"call","fileName":"Closure.java","lineNumber":412},{"declaringClass":"groovy.lang.Closure","methodName":"call","fileName":"Closure.java","lineNumber":428},{"declaringClass":"io.restassured.assertion.BodyMatcherGroup","methodName":"validate","fileName":"BodyMatcherGroup.groovy","lineNumber":47},{"declaringClass":"io.restassured.internal.ResponseSpecificationImpl","methodName":"validateResponseIfRequired","fileName":"ResponseSpecificationImpl.groovy","lineNumber":674},{"declaringClass":"io.restassured.internal.ResponseSpecificationImpl","methodName":"body","fileName":"ResponseSpecificationImpl.groovy","lineNumber":98},{"declaringClass":"io.restassured.internal.ValidatableResponseOptionsImpl","methodName":"body","fileName":"ValidatableResponseOptionsImpl.java","lineNumber":238},{"declaringClass":"io.restassured.internal.ValidatableResponseImpl","methodName":"super$2$body","fileName":"ValidatableResponseImpl.groovy","lineNumber":-1},{"declaringClass":"groovy.lang.MetaMethod","methodName":"doMethodInvoke","fileName":"MetaMethod.java","lineNumber":323},{"declaringClass":"groovy.lang.MetaClassImpl","methodName":"invokeMethod","fileName":"MetaClassImpl.java","lineNumber":1267},{"declaringClass":"io.restassured.internal.ValidatableResponseImpl","methodName":"body","fileName":"ValidatableResponseImpl.groovy","lineNumber":293},{"declaringClass":"io.restassured.internal.ValidatableResponseImpl","methodName":"body","fileName":"ValidatableResponseImpl.groovy","lineNumber":-1},{"declaringClass":"starter.JsonPlaceHolder.Comments.GetCommentsStepDef","methodName":"validateJsonSchemaListComments","fileName":"GetCommentsStepDef.java","lineNumber":46},{"declaringClass":"io.cucumber.java.Invoker","methodName":"doInvoke","fileName":"Invoker.java","lineNumber":66},{"declaringClass":"io.cucumber.java.Invoker","methodName":"invoke","fileName":"Invoker.java","lineNumber":24},{"declaringClass":"io.cucumber.java.AbstractGlueDefinition","methodName":"invokeMethod","fileName":"AbstractGlueDefinition.java","lineNumber":47},{"declaringClass":"io.cucumber.java.JavaStepDefinition","methodName":"execute","fileName":"JavaStepDefinition.java","lineNumber":29},{"declaringClass":"io.cucumber.core.runner.CoreStepDefinition","methodName":"execute","fileName":"CoreStepDefinition.java","lineNumber":66},{"declaringClass":"io.cucumber.core.runner.PickleStepDefinitionMatch","methodName":"runStep","fileName":"PickleStepDefinitionMatch.java","lineNumber":63},{"declaringClass":"io.cucumber.core.runner.TestStep","methodName":"executeStep","fileName":"TestStep.java","lineNumber":92},{"declaringClass":"io.cucumber.core.runner.TestStep","methodName":"run","fileName":"TestStep.java","lineNumber":64},{"declaringClass":"io.cucumber.core.runner.PickleStepTestStep","methodName":"run","fileName":"PickleStepTestStep.java","lineNumber":51},{"declaringClass":"io.cucumber.core.runner.TestCase","methodName":"run","fileName":"TestCase.java","lineNumber":104},{"declaringClass":"io.cucumber.core.runner.Runner","methodName":"runPickle","fileName":"Runner.java","lineNumber":73},{"declaringClass":"io.cucumber.junit.FeatureRunner","methodName":"runChild","fileName":"FeatureRunner.java","lineNumber":135},{"declaringClass":"io.cucumber.junit.FeatureRunner","methodName":"runChild","fileName":"FeatureRunner.java","lineNumber":27},{"declaringClass":"io.cucumber.junit.CucumberSerenityRunner","methodName":"runChild","fileName":"CucumberSerenityRunner.java","lineNumber":258},{"declaringClass":"io.cucumber.junit.CucumberSerenityRunner","methodName":"runChild","fileName":"CucumberSerenityRunner.java","lineNumber":57}]},"testFailureClassname":"net.serenitybdd.core.exceptions.UnrecognisedException","testFailureSummary":"ERROR;net.serenitybdd.core.exceptions.UnrecognisedException;null;JsonParser.java","projectKey":"","annotatedResult":"ERROR","isManualTestingUpToDate":false,"manual":false,"testSource":"Cucumber","result":"ERROR"}